{
  "Hardware_Mapping": {
    "MCU": "ESP32-S3-N4R8 (PlatformIO env: esp32-s3-n4r8, Arduino framework)",
    "CKP_Output": {
      "Pin": "GPIO17 (PIN_CKP_OUT)",
      "Timer": "ESP32 HW timer (timerBegin @ 1MHz base)",
      "Driver": "TimerCkpGenerator"
    },
    "Capture_Input": {
      "Pin": "GPIO18 (PIN_CAPTURE_IN)",
      "Interrupt": "GPIO edge interrupt (CHANGE)",
      "Driver": "EdgePulseCapture",
      "Notes": "Comment in src/main.cpp mentions GPIO16; confirm wiring."
    },
    "Display": {
      "Panel": "Guiton JC4827W543",
      "Resolution": "480x272",
      "Interface": "Arduino_GFX (RGB panel) via Dev Device Pins",
      "Pinout_Source": "PINS_JC4827W543.h (Dev Device Pins library)",
      "Backlight": "GFX_BL macro from PINS_JC4827W543.h"
    },
    "Touch": {
      "Controller": "GT911",
      "Bus": "I2C (Wire)",
      "Pins": {
        "SDA": "GPIO8",
        "SCL": "GPIO4",
        "INT": "GPIO3",
        "RST": "GPIO38"
      },
      "Resolution": "480x272",
      "Source": "test/JC4827W543_LVGLv9.txt"
    }
  },
  "UI_Logic_Contract": {
    "UI_API": {
      "ui_init": "void ui_init(ui_on_rpm_cb on_rpm, ui_on_pattern_cb on_pattern)",
      "ui_task_handler": "void ui_task_handler()"
    },
    "UI_to_App": {
      "UI_EVT_RPM_CHANGED": {
        "Callback": "ui_on_rpm_cb(uint32_t rpm)",
        "Message": "CtrlMsg{type=MSG_SET_RPM, payload.val=rpm}",
        "Range": "100..6000"
      },
      "UI_EVT_PATTERN_CHANGED": {
        "Callback": "ui_on_pattern_cb(uint8_t index)",
        "Message": "CtrlMsg{type=MSG_SET_PATTERN, payload.val=index}",
        "Options": [
          "60-2",
          "36-1",
          "36-2",
          "36-1-1"
        ],
        "Index_Map": {
          "0": "60-2",
          "1": "36-1",
          "2": "36-2",
          "3": "36-1-1"
        }
      }
    },
    "App_to_UI": {
      "UI_EVT_STATUS_SYNC": {
        "Optional": true,
        "Payload": "{rpm, pattern_index}",
        "Purpose": "Keep arc/dropdown synced if backend changes state."
      }
    }
  },
  "Current_Status": {
    "Phase": "UI bring-up: orientation, layout, touch alignment",
    "Findings": [
      "Display is showing portrait because gfx->setRotation uses a GT911 rotation constant; display rotation and touch rotation are likely mismatched.",
      "Arc and dropdown overlap due to mid-screen alignment; layout needs top-left and top-right anchors for landscape.",
      "Arc drag and dropdown selection are inconsistent, indicating touch coordinates are not mapped to display coordinates.",
      "lv_indev_set_display is not called; input device may not be tied to the active display."
    ],
    "Conflicts": [
      "Rotation constants for GT911 (ROTATION_*) are not guaranteed to match Arduino_GFX rotation values."
    ],
    "Pending_Tasks": [
      "Set landscape rotation for display and touch using explicit rotation constants per library, and update GT911 resolution to match the rotated display.",
      "Bind the LVGL input device to the active display with lv_indev_set_display.",
      "Re-layout arc and dropdown to top-left/top-right for landscape with explicit margins.",
      "Verify arc direction (right increases, left decreases) and adjust arc mode/angles if needed.",
      "Ensure dropdown selection uses correct touch mapping after rotation changes."
    ],
    "Notes": [
      "Touch pins from reference: SDA=8, SCL=4, INT=3, RST=38.",
      "UI must clamp RPM to 100..6000 and map dropdown index 0..3 to patternFromIndex().",
      "Current symptoms: portrait orientation, overlap, arc drag at random points, dropdown selection not registering."
    ]
  }
}
